LICENSE
MANIFEST.in
README.rst
pghoard.json
pghoard.unit
setup.py
version.py
pghoard/__init__.py
pghoard/__main__.py
pghoard/archive_cleanup.py
pghoard/archive_sync.py
pghoard/basebackup.py
pghoard/common.py
pghoard/compressor.py
pghoard/config.py
pghoard/create_keys.py
pghoard/fetcher.py
pghoard/gnutaremu.py
pghoard/logutil.py
pghoard/mapping.py
pghoard/metrics.py
pghoard/patchedtarfile.py
pghoard/pghoard.py
pghoard/pgutil.py
pghoard/postgres_command.py
pghoard/receivexlog.py
pghoard/restore.py
pghoard/transfer.py
pghoard/version.py
pghoard/wal.py
pghoard/walreceiver.py
pghoard/webserver.py
pghoard.egg-info/PKG-INFO
pghoard.egg-info/SOURCES.txt
pghoard.egg-info/dependency_links.txt
pghoard.egg-info/entry_points.txt
pghoard.egg-info/not-zip-safe
pghoard.egg-info/requires.txt
pghoard.egg-info/top_level.txt
pghoard/monitoring/__init__.py
pghoard/monitoring/prometheus.py
pghoard/monitoring/pushgateway.py
pghoard/monitoring/statsd.py
pghoard/rohmu/__init__.py
pghoard/rohmu/compat.py
pghoard/rohmu/compressor.py
pghoard/rohmu/dates.py
pghoard/rohmu/encryptor.py
pghoard/rohmu/errors.py
pghoard/rohmu/filewrap.py
pghoard/rohmu/inotify.py
pghoard/rohmu/rohmufile.py
pghoard/rohmu/snappyfile.py
pghoard/rohmu/zstdfile.py
pghoard/rohmu/object_storage/__init__.py
pghoard/rohmu/object_storage/azure.py
pghoard/rohmu/object_storage/base.py
pghoard/rohmu/object_storage/google.py
pghoard/rohmu/object_storage/local.py
pghoard/rohmu/object_storage/s3.py
pghoard/rohmu/object_storage/sftp.py
pghoard/rohmu/object_storage/swift.py
test/__init__.py
test/base.py
test/conftest.py
test/test_archivesync.py
test/test_basebackup.py
test/test_common.py
test/test_compressor.py
test/test_create_keys.py
test/test_encryptor.py
test/test_inotify.py
test/test_pghoard.py
test/test_pgutil.py
test/test_restore.py
test/test_rohmu_dates.py
test/test_storage.py
test/test_storage_configs.py
test/test_transferagent.py
test/test_wal.py
test/test_webserver.py