Metadata-Version: 1.1
Name: pghoard
Version: 2.1.0
Summary: PostgreSQL automatic backup/restore service daemon
Home-page: https://github.com/aiven/pghoard/
Author: Hannu Valtonen
Author-email: hannu.valtonen@ohmu.fi
License: Apache 2.0
Platform: POSIX
Platform: MacOS
Classifier: Development Status :: 5 - Production/Stable
Classifier: Intended Audience :: Developers
Classifier: Intended Audience :: Information Technology
Classifier: Intended Audience :: System Administrators
Classifier: License :: OSI Approved :: Apache Software License
Classifier: Programming Language :: Python :: 3.3
Classifier: Programming Language :: Python :: 3.4
Classifier: Programming Language :: Python :: 3.5
Classifier: Programming Language :: Python :: 3.6
Classifier: Topic :: Database :: Database Engines/Servers
Classifier: Topic :: Software Development :: Libraries
